colorie.py
colorie-0.1.2.dist-info/LICENSE
colorie-0.1.2.dist-info/WHEEL
colorie-0.1.2.dist-info/METADATA
colorie-0.1.2.dist-info/RECORD
