Metadata-Version: 2.1
Name: colorie
Version: 0.1.2
Summary: ANSII Color formatting for output in terminal
Home-page: https://github.com/Ovsyanka83/colorie
License: MIT
Author: Ovsyanka83
Author-email: szmiev2000@gmail.com
Requires-Python: >=3.6,<4.0
Classifier: Development Status :: 5 - Production/Stable
Classifier: Environment :: Console
Classifier: Intended Audience :: Developers
Classifier: License :: OSI Approved :: MIT License
Classifier: Operating System :: OS Independent
Classifier: Programming Language :: Python
Classifier: Programming Language :: Python :: 3
Classifier: Programming Language :: Python :: 3.10
Classifier: Programming Language :: Python :: 3.6
Classifier: Programming Language :: Python :: 3.7
Classifier: Programming Language :: Python :: 3.8
Classifier: Programming Language :: Python :: 3.9
Classifier: Topic :: Terminals
Project-URL: Repository, https://github.com/Ovsyanka83/colorie
